conf_d/__init__.py
conf_d/compat.py
conf_d-0.1.0.dist-info/LICENSE.txt
conf_d-0.1.0.dist-info/METADATA
conf_d-0.1.0.dist-info/WHEEL
conf_d-0.1.0.dist-info/top_level.txt
conf_d-0.1.0.dist-info/RECORD
