Metadata-Version: 2.1
Name: conf-d
Version: 0.1.0
Summary: read configuration files, conf.d style
Home-page: http://github.com/josegonzalez/conf_d
Author: Jose Diaz-Gonzalez
Author-email: conf_d@josediazgonzalez.com
License: LICENSE.txt
Platform: UNKNOWN
Classifier: Development Status :: 5 - Production/Stable
Classifier: Intended Audience :: System Administrators
Classifier: License :: OSI Approved :: MIT License
Classifier: Programming Language :: Python :: 2.6
Classifier: Programming Language :: Python :: 2.7
Classifier: Programming Language :: Python :: 3.4
Classifier: Programming Language :: Python :: 3.5
Classifier: Programming Language :: Python :: 3.6
Classifier: Programming Language :: Python :: 3.7
